compact_frame_format/__init__.py
compact_frame_format/cff.py
compact_frame_format-1.0.0rc2.dist-info/licenses/LICENSE
compact_frame_format-1.0.0rc2.dist-info/METADATA
compact_frame_format-1.0.0rc2.dist-info/WHEEL
compact_frame_format-1.0.0rc2.dist-info/top_level.txt
compact_frame_format-1.0.0rc2.dist-info/RECORD
