Metadata-Version: 2.4
Name: compact-frame-format
Version: 1.0.0rc2
Summary: Python reference implementation of Compact Frame Format, a simple, low-overhead frame format designed for fast, reliable serial links.
Author: R. Keelan
License: MIT License
Project-URL: Homepage, https://github.com/CompactFrameFormat/cff-python
Project-URL: Changelog, https://github.com/CompactFrameFormat/cff-python/releases
Project-URL: Issues, https://github.com/CompactFrameFormat/cff-python/issues
Project-URL: CI, https://github.com/CompactFrameFormat/cff-python/actions
Requires-Python: >=3.9
License-File: LICENSE
Provides-Extra: test
Requires-Dist: pytest; extra == "test"
Requires-Dist: pytest-cov; extra == "test"
Provides-Extra: dev
Requires-Dist: ruff; extra == "dev"
Requires-Dist: pre-commit; extra == "dev"
Dynamic: license-file
